gwapandas/__init__.py
gwapandas/cli.py
gwapandas/gwapandas.py
gwapandas/sumstats.py
gwapandas-0.0.2.dist-info/WHEEL
gwapandas-0.0.2.dist-info/entry_points.txt
gwapandas-0.0.2.dist-info/LICENSE
gwapandas-0.0.2.dist-info/METADATA
gwapandas-0.0.2.dist-info/RECORD
