Metadata-Version: 2.1
Name: gwapandas
Version: 0.0.2
Summary: Python tools for GWAS summary statistics.
Home-page: https://github.com/Jianhua-Wang/gwapandas
License: MIT
Author: Jianhua Wang
Author-email: jianhua.mert@gmail.com
Requires-Python: >=3.7,<3.12
Classifier: Development Status :: 2 - Pre-Alpha
Classifier: Intended Audience :: Developers
Classifier: License :: OSI Approved :: MIT License
Classifier: Natural Language :: English
Classifier: Programming Language :: Python :: 3
Classifier: Programming Language :: Python :: 3.7
Classifier: Programming Language :: Python :: 3.8
Classifier: Programming Language :: Python :: 3.9
Classifier: Programming Language :: Python :: 3.10
Classifier: Programming Language :: Python :: 3.11
Classifier: Programming Language :: Python :: 3
Classifier: Programming Language :: Python :: 3.7
Classifier: Programming Language :: Python :: 3.8
Classifier: Programming Language :: Python :: 3.9
Provides-Extra: dev
Provides-Extra: doc
Provides-Extra: test
Requires-Dist: black (>=22.3.0) ; extra == "test"
Requires-Dist: bump2version (>=1.0.1,<2.0.0) ; extra == "dev"
Requires-Dist: flake8 (>=3.9.2,<4.0.0) ; extra == "test"
Requires-Dist: flake8-docstrings (>=1.6.0,<2.0.0) ; extra == "test"
Requires-Dist: isort (>=5.8.0,<6.0.0) ; extra == "test"
Requires-Dist: mkdocs (>=1.4.2,<2.0.0) ; extra == "doc"
Requires-Dist: mkdocs-autorefs (>=0.4.1,<0.5.0) ; extra == "doc"
Requires-Dist: mkdocs-include-markdown-plugin (>=4.0.3,<5.0.0) ; extra == "doc"
Requires-Dist: mkdocs-material (>=8.5.11,<9.0.0) ; extra == "doc"
Requires-Dist: mkdocs-material-extensions (>=1.1.1,<2.0.0)
Requires-Dist: mkdocstrings[python] (>=0.19.1,<0.20.0) ; extra == "doc"
Requires-Dist: mypy (>=0.900,<0.901) ; extra == "test"
Requires-Dist: pip (>=20.3.1,<21.0.0) ; extra == "dev"
Requires-Dist: pre-commit (>=2.12.0,<3.0.0) ; extra == "dev"
Requires-Dist: pytest (>=6.2.4,<7.0.0) ; extra == "test"
Requires-Dist: pytest-cov (>=2.12.0,<3.0.0) ; extra == "test"
Requires-Dist: toml (>=0.10.2,<0.11.0) ; extra == "dev"
Requires-Dist: tox (>=3.20.1,<4.0.0) ; extra == "dev"
Requires-Dist: twine (>=3.3.0,<4.0.0) ; extra == "dev"
Requires-Dist: typer (>=0.7.0,<0.8.0)
Requires-Dist: virtualenv (>=20.2.2,<21.0.0) ; extra == "dev"
